sleepystuffey/__init__.py
sleepystuffey/sleep.py
sleepystuffey-0.0.1.dist-info/METADATA
sleepystuffey-0.0.1.dist-info/WHEEL
sleepystuffey-0.0.1.dist-info/top_level.txt
sleepystuffey-0.0.1.dist-info/RECORD
