Metadata-Version: 2.1
Name: sleepystuffey
Version: 0.0.1
Summary: Automated Reddit to Instagram
Home-page: UNKNOWN
Author: Sarah Feucht
Author-email: <feuchtesari@gmail.com>
License: UNKNOWN
Keywords: python,sleep
Platform: UNKNOWN
